{
	"Default": {
		"Fg": "Foreground",
		"Bg": "Background"
	},
	"Error": {
		"Fg": "Red"
	},
	"Warning": {
		"Fg": "Yellow"
	},
	"TabBar": {
		"Bg": "BrightWhite"
	},
	"CurrentTab": {
		"Bold": true,
		"Bg": "White"
	},
	"LineNum": {
		"Fg": "BrightBlack"
	},
	"Whitespace": {
		"Fg": "White"
	},
	"Cursor": {
		"Bg": "Foreground",
		"Fg": "Background"
	},
	"CursorWord": {
		"Bg": "BrightWhite"
	},
	"Find": {
		"Bg": "BrightYellow"
	},
	"Selection": {
		"Bg": "Red",
		"Fg": "Background"
	},
	"MatchingBracket": {
		"Bg": "Black",
		"Fg": "BrightWhite",
		"Bold": true
	},
	"StatusLine": {
		"Bg": "BrightWhite"
	},
	"RepCount": {
		"Bg": "BrightWhite",
		"Fg": "Cyan"
	},
	"StateMark": {
		"Bg": "BrightWhite",
		"Fg": "Green"
	},
	"FindMark": {
		"Bg": "BrightWhite",
		"Fg": "Yellow"
	},
	"PromptShadow": {
		"Fg": "BrightBlack"
	},
	"Menu": {
		"Bg": "BrightWhite"
	},
	"MenuItem": {
		"Bg": "White",
		"Bold": true
	},
	"Attribute": {
		"Fg": "Cyan"
	},
	"Bold": {
		"Bold": true
	},
	"Comment": {
		"Fg": "Black"
	},
	"Heading": {
		"Fg": "BrightRed"
	},
	"Italic": {
		"Italic": true
	},
	"Keyword": {
		"Fg": "Blue"
	},
	"Meta": {
		"Fg": "Magenta"
	},
	"Mono": {
		"Fg": "Magenta"
	},
	"Number": {
		"Fg": "Red"
	},
	"Operator": {
		"Fg": "Magenta"
	},
	"String": {
		"Fg": "Green"
	},
	"Type": {
		"Fg": "Yellow"
	},
	"Value": {
		"Fg": "Red"
	},
	"Variable": {
		"Fg": "BrightRed"
	}
}
